monitor_utility/BalanceUtility.py
monitor_utility/RpcProviderUtility.py
monitor_utility/StoremanUtility.py
monitor_utility/TokenPairsUtility.py
monitor_utility/UpdateConfigUtility.py
monitor_utility/__init__.py
monitor_utility/hex_string_convert.py
monitor_utility/multicallUtility.py
monitor_utility-0.0.18.dist-info/METADATA
monitor_utility-0.0.18.dist-info/WHEEL
monitor_utility-0.0.18.dist-info/top_level.txt
monitor_utility-0.0.18.dist-info/RECORD
