Metadata-Version: 2.1
Name: monitor-utility
Version: 0.0.18
Summary: simple tool
Home-page: https://github.com/Nevquit/monitor_utility
Author: vSir
Author-email: weiguo341@gmail.com
Classifier: Programming Language :: Python :: 3
Classifier: License :: OSI Approved :: MIT License
Classifier: Operating System :: OS Independent
Requires-Dist: iWAN
Requires-Dist: iWAN-Request
Requires-Dist: pubkey2address
Requires-Dist: substrate-interface (==1.1)
Requires-Dist: websocket-client (==0.58.0)
Requires-Dist: BalanceSpider
Requires-Dist: multicall (==0.1.2)
Requires-Dist: web3 (==5.28.0)
